{
  "$schema": "https://mintlify.com/docs.json",
  "name": "Secure Link API",
  "theme": "sequoia",
  "colors": {
    "primary": "#7c7c80",
    "light": "#151c28",
    "dark": "#f2f2f2"
  },
  "favicon": "https://media.brand.dev/ed1ea708-4249-4d42-9233-93fde61f32fc.jpg",
  "logo": {
    "light": "https://media.brand.dev/ed1ea708-4249-4d42-9233-93fde61f32fc.jpg",
    "dark": "https://media.brand.dev/ed1ea708-4249-4d42-9233-93fde61f32fc.jpg"
  },
  "navbar": {
    "primary": {
      "type": "github",
      "href": "https://github.com/WalysonGomes/secure-link-api"
    }
  },
  "footer": {
    "socials": {
      "github": "https://github.com/WalysonGomes/secure-link-api"
    }
  },
  "navigation": {
    "tabs": [
      {
        "tab": "Documentation",
        "groups": [
          {
            "group": "Get Started",
            "pages": [
              "introduction",
              "quickstart"
            ]
          },
          {
            "group": "Core Concepts",
            "pages": [
              "concepts/secure-links",
              "concepts/access-control",
              "concepts/audit-tracking"
            ]
          },
          {
            "group": "Guides",
            "pages": [
              "guides/creating-links",
              "guides/uploading-files",
              "guides/password-protection",
              "guides/link-expiration",
              "guides/revocation"
            ]
          }
        ]
      },
      {
        "tab": "API Reference",
        "groups": [
          {
            "group": "Overview",
            "pages": [
              "api/overview",
              "api/authentication",
              "api/error-handling"
            ]
          },
          {
            "group": "Links",
            "pages": [
              "api/links/create",
              "api/links/upload",
              "api/links/resolve",
              "api/links/revoke"
            ]
          },
          {
            "group": "Statistics",
            "pages": [
              "api/stats/overview",
              "api/stats/access-summary",
              "api/stats/security-metrics"
            ]
          }
        ]
      },
      {
        "tab": "Operations",
        "groups": [
          {
            "group": "Deployment",
            "pages": [
              "operations/installation",
              "operations/configuration",
              "operations/docker"
            ]
          },
          {
            "group": "Monitoring",
            "pages": [
              "operations/health-checks",
              "operations/metrics",
              "operations/observability"
            ]
          }
        ]
      }
    ]
  }
}
